registerer/__init__.py
registerer/exceptions.py
registerer/registry.py
registerer/validators.py
registerer-1.0.0.dist-info/METADATA
registerer-1.0.0.dist-info/WHEEL
registerer-1.0.0.dist-info/licenses/LICENSE
registerer-1.0.0.dist-info/RECORD
