Metadata-Version: 2.4
Name: registerer
Version: 1.0.0
Summary: Everything you need to implement maintainable and easy to use registry patterns in your project.
License: MIT
License-File: LICENSE
Author: Danial Keimasi
Author-email: danialkeimasi@gmail.com
Requires-Python: >=3.9,<4.0
Classifier: License :: OSI Approved :: MIT License
Classifier: Programming Language :: Python :: 3
Classifier: Programming Language :: Python :: 3.9
Classifier: Programming Language :: Python :: 3.10
Classifier: Programming Language :: Python :: 3.11
Classifier: Programming Language :: Python :: 3.12
Classifier: Programming Language :: Python :: 3.13
Classifier: Programming Language :: Python :: 3.14
Classifier: Topic :: Software Development :: Build Tools
Classifier: Topic :: Software Development :: Libraries :: Python Modules
Project-URL: Bug Tracker, https://github.com/danialkeimasi/python-registerer/issues
Project-URL: Homepage, https://github.com/danialkeimasi/python-registerer
